pycounts_akhras/__init__.py
pycounts_akhras/plotting.py
pycounts_akhras/pycounts_akhras.py
pycounts_akhras-0.1.0.dist-info/LICENSE
pycounts_akhras-0.1.0.dist-info/METADATA
pycounts_akhras-0.1.0.dist-info/WHEEL
pycounts_akhras-0.1.0.dist-info/RECORD
